vss_ctx_rag/plugins/__init__.py
vss_ctx_rag/plugins/arango/__init__.py
vss_ctx_rag/plugins/arango/arango_db.py
vss_ctx_rag/plugins/arango/networkx_db.py
vss_ctx_rag_arango-1.0.1.dist-info/METADATA
vss_ctx_rag_arango-1.0.1.dist-info/WHEEL
vss_ctx_rag_arango-1.0.1.dist-info/top_level.txt
vss_ctx_rag_arango-1.0.1.dist-info/RECORD
