Metadata-Version: 2.4
Name: vss_ctx_rag_arango
Version: 1.0.1
Summary: Subpackage for Arango Integration in vss_ctx_rag
Requires-Python: >=3.11
Requires-Dist: vss_ctx_rag
Requires-Dist: python-arango>=8.1.6
Requires-Dist: nx-arangodb>=1.3.0
Requires-Dist: cuml-cu12>=25.4.0
Requires-Dist: cupy-cuda12x==13.4.1
Requires-Dist: nx-cugraph-cu12>=25.4.0
Requires-Dist: langchain-arangodb>=1.2.0
